textual_sortable_datatable/__init__.py
textual_sortable_datatable/sortable_data_table.py
textual_sortable_datatable-0.1.0.dist-info/METADATA
textual_sortable_datatable-0.1.0.dist-info/WHEEL
textual_sortable_datatable-0.1.0.dist-info/entry_points.txt
textual_sortable_datatable-0.1.0.dist-info/RECORD
