Metadata-Version: 2.4
Name: textual-sortable-datatable
Version: 0.1.0
Summary: Add your description here
Author-email: Patrick de Koning <pjhdekoning@lumc.nl>
Requires-Python: >=3.13
Requires-Dist: pandas>=2
Requires-Dist: textual>=1.0
